Metadata-Version: 2.1
Name: neon-tts-plugin-audiofiles
Version: 0.0.3
Summary: A "TTS" plugin for Neon
Home-page: https://github.com/NeonGeckoCom/neon-tts-plugin-audiofiles
Author: Neongecko
Author-email: developers@neon.ai
License: BSD-3.0
Keywords: mycroft plugin tts
Classifier: Intended Audience :: Developers
Classifier: Topic :: Text Processing :: Linguistic
Classifier: Programming Language :: Python :: 3.6
License-File: LICENSE.md
Requires-Dist: neon-utils~=1.0
Requires-Dist: ovos-plugin-manager>=0.0.2,~=0.0
Requires-Dist: ovos-utils>=0.0.25,~=0.0
Requires-Dist: ovos-config>=0.0.4,~=0.0
Requires-Dist: ovos-workshop>=0.0.9,~=0.0
